dotorm/__init__.py
dotorm/access.py
dotorm/decorators.py
dotorm/exceptions.py
dotorm/fields.py
dotorm/model.py
dotorm/builder/__init__.py
dotorm/builder/builder.py
dotorm/builder/helpers.py
dotorm/builder/protocol.py
dotorm/builder/request_builder.py
dotorm/builder/mixins/__init__.py
dotorm/builder/mixins/crud.py
dotorm/builder/mixins/m2m.py
dotorm/builder/mixins/relations.py
dotorm/components/__init__.py
dotorm/components/dialect.py
dotorm/components/filter_parser.py
dotorm/databases/__init__.py
dotorm/databases/abstract/__init__.py
dotorm/databases/abstract/dialect.py
dotorm/databases/abstract/pool.py
dotorm/databases/abstract/session.py
dotorm/databases/abstract/types.py
dotorm/databases/clickhouse/__init__.py
dotorm/databases/clickhouse/pool.py
dotorm/databases/clickhouse/session.py
dotorm/databases/mysql/__init__.py
dotorm/databases/mysql/pool.py
dotorm/databases/mysql/session.py
dotorm/databases/mysql/transaction.py
dotorm/databases/postgres/__init__.py
dotorm/databases/postgres/pool.py
dotorm/databases/postgres/session.py
dotorm/databases/postgres/transaction.py
dotorm/integrations/__init__.py
dotorm/integrations/pydantic.py
dotorm/orm/__init__.py
dotorm/orm/protocol.py
dotorm/orm/utils.py
dotorm/orm/mixins/__init__.py
dotorm/orm/mixins/access.py
dotorm/orm/mixins/ddl.py
dotorm/orm/mixins/many2many.py
dotorm/orm/mixins/primary.py
dotorm/orm/mixins/relations.py
dotorm-2.0.9.dist-info/METADATA
dotorm-2.0.9.dist-info/WHEEL
dotorm-2.0.9.dist-info/licenses/LICENSE
dotorm-2.0.9.dist-info/RECORD
