Metadata-Version: 2.4
Name: dotorm
Version: 2.0.9
Summary: Async Python ORM for PostgreSQL, MySQL and ClickHouse with dot-notation access
Project-URL: Homepage, https://github.com/shurshilov/dotorm
Project-URL: Repository, https://github.com/shurshilov/dotorm
Project-URL: Issues, https://github.com/shurshilov/dotorm/issues
Author-email: shurshilov <shurshilov.s@yandex.ru>
License: MIT
License-File: LICENSE
Keywords: async,asyncio,clickhouse,database,mysql,orm,postgresql
Classifier: Development Status :: 4 - Beta
Classifier: Framework :: AsyncIO
Classifier: Intended Audience :: Developers
Classifier: License :: OSI Approved :: MIT License
Classifier: Operating System :: OS Independent
Classifier: Programming Language :: Python :: 3
Classifier: Programming Language :: Python :: 3.12
Classifier: Programming Language :: Python :: 3.13
Classifier: Topic :: Database
Classifier: Topic :: Software Development :: Libraries :: Python Modules
Classifier: Typing :: Typed
Requires-Python: >=3.12
Provides-Extra: all
Requires-Dist: aiomysql>=0.2.0; extra == 'all'
Requires-Dist: asynch>=0.2.0; extra == 'all'
Requires-Dist: asyncpg>=0.29.0; extra == 'all'
Requires-Dist: pydantic-settings>=2.0.0; extra == 'all'
Requires-Dist: pydantic>=2.0.0; extra == 'all'
Provides-Extra: clickhouse
Requires-Dist: asynch>=0.2.0; extra == 'clickhouse'
Provides-Extra: dev
Requires-Dist: pytest-asyncio>=0.23.0; extra == 'dev'
Requires-Dist: pytest>=8.0.0; extra == 'dev'
Requires-Dist: ruff>=0.4.0; extra == 'dev'
Provides-Extra: mysql
Requires-Dist: aiomysql>=0.2.0; extra == 'mysql'
Provides-Extra: postgres
Requires-Dist: asyncpg>=0.29.0; extra == 'postgres'
Provides-Extra: pydantic
Requires-Dist: pydantic-settings>=2.0.0; extra == 'pydantic'
Requires-Dist: pydantic>=2.0.0; extra == 'pydantic'
